PySide6QtAds/PySide6QtAds.pyd
PySide6QtAds/__init__.py
PySide6QtAds/license/ads/LICENSE
PySide6QtAds/license/ads/gnu-lgpl-v2.1.md
pyside6_qtads-4.5.0.dist-info/licenses/LICENSE.txt
pyside6_qtads-4.5.0.dist-info/METADATA
pyside6_qtads-4.5.0.dist-info/WHEEL
pyside6_qtads-4.5.0.dist-info/top_level.txt
pyside6_qtads-4.5.0.dist-info/RECORD
