Metadata-Version: 2.4
Name: PySide6-QtAds
Version: 4.5.0
Summary: PySide6 bindings to Qt Advanced Docking System
License: PySide6-QtAds is licensed under GNU LGPL v2.1.
Project-URL: Homepage, https://github.com/mborgerson/pyside6_qtads/
Classifier: Development Status :: 3 - Alpha
Classifier: Intended Audience :: Developers
Classifier: Programming Language :: Python :: 3
Requires-Python: >=3.9
License-File: LICENSE.txt
Requires-Dist: PySide6-Essentials==6.10.1
Requires-Dist: shiboken6==6.10.1
Dynamic: license-file
Dynamic: requires-dist
